dm_streamvalve/.gitignore
dm_streamvalve/__init__.py
dm_streamvalve/py.typed
dm_streamvalve/streamvalve.py
dm_streamvalve-0.1.1.dist-info/METADATA
dm_streamvalve-0.1.1.dist-info/WHEEL
dm_streamvalve-0.1.1.dist-info/licenses/LICENSE
dm_streamvalve-0.1.1.dist-info/RECORD
