Metadata-Version: 2.4
Name: dm-streamvalve
Version: 0.1.1
Summary: Reconstruct a text string from an Iterable, with optional stopping criteria
Project-URL: Homepage, https://github.com/DrMicrobit/dm-streamvalve
Project-URL: GitHub, https://github.com/DrMicrobit/dm-streamvalve
Project-URL: Issues, https://github.com/DrMicrobit/dm-streamvalve/issues
Author-email: Bastien Chevreux <bach@chevreux.org>
License-Expression: MIT
License-File: LICENSE
Classifier: Development Status :: 5 - Production/Stable
Classifier: Intended Audience :: Developers
Classifier: License :: OSI Approved :: MIT License
Classifier: Operating System :: OS Independent
Classifier: Programming Language :: Python :: 3
Requires-Python: >=3.13
